pydingtalk/__init__.py
pydingtalk/__version__.py
pydingtalk/bot.py
pydingtalk/errors.py
pydingtalk/log.py
PyDingTalk-0.1.2.dist-info/LICENSE
PyDingTalk-0.1.2.dist-info/METADATA
PyDingTalk-0.1.2.dist-info/WHEEL
PyDingTalk-0.1.2.dist-info/top_level.txt
PyDingTalk-0.1.2.dist-info/RECORD
