Metadata-Version: 2.1
Name: PyDingTalk
Version: 0.1.2
Summary: This is a msg-robot for DingTalk.
Home-page: https://github.com/liukecode/pydingtalk
Author: LiukeCode
Maintainer: Liuke
License: MIT
Keywords: dingding,dingtalk,api,bot,robot
Classifier: Development Status :: 5 - Production/Stable
Classifier: Intended Audience :: Developers
Classifier: Intended Audience :: End Users/Desktop
Classifier: Intended Audience :: Information Technology
Classifier: Intended Audience :: System Administrators
Classifier: License :: OSI Approved :: MIT License
Classifier: Programming Language :: Python :: 3.7
Classifier: Programming Language :: Python :: 3.8
Classifier: Programming Language :: Python :: 3.9
Classifier: Programming Language :: Python :: 3.10
Classifier: Topic :: Communications
Classifier: Topic :: Office/Business
Requires-Python: >=3.7
License-File: LICENSE
Requires-Dist: requests (==2.26.0)
Requires-Dist: tenacity (==8.0.1)
